.travis.yml
AUTHORS
CHANGES
LICENSE
MANIFEST.in
README
requirements.txt
setup.py
lantz/drivers/__init__.py
lantz/drivers/ieee4882.py
lantz/drivers/lantz_server.py
lantz/drivers/scpi.py
lantz/drivers/aa/__init__.py
lantz/drivers/aa/aotf.py
lantz/drivers/acton/sp2150i.py
lantz/drivers/aeroflex/__init__.py
lantz/drivers/aeroflex/a2023a.py
lantz/drivers/agilent/AG33522a.py
lantz/drivers/agilent/__init__.py
lantz/drivers/agilent/ag33220A.py
lantz/drivers/agilent/ag81130a.py
lantz/drivers/agilent/e8257c.py
lantz/drivers/agilent/n51xx.py
lantz/drivers/alliedvision/__init__.py
lantz/drivers/alliedvision/vimba.py
lantz/drivers/alliedvision/tests/vimbatest.py
lantz/drivers/amplifier_research/__init__.py
lantz/drivers/amplifier_research/arxx.py
lantz/drivers/andor/__init__.py
lantz/drivers/andor/andor.py
lantz/drivers/andor/ccd.py
lantz/drivers/andor/neo.py
lantz/drivers/arduino/__init__.py
lantz/drivers/arduino/goniometer.py
lantz/drivers/arduino/gonioupdated.ino
lantz/drivers/arduino/gonioupdated/gonioupdated.ino
lantz/drivers/attocube/__init__.py
lantz/drivers/attocube/anc350.py
lantz/drivers/attocube/anc350v3.dll
lantz/drivers/attocube/anc350v3.lib
lantz/drivers/basler/__init__.py
lantz/drivers/basler/basler.py
lantz/drivers/basler/props.txt
lantz/drivers/berkeleynucleonics/__init__.py
lantz/drivers/berkeleynucleonics/bnc645.py
lantz/drivers/bkprecision/bk9129b.py
lantz/drivers/bristol/__init__.py
lantz/drivers/bristol/bristol621.py
lantz/drivers/bristol/bristol671.py
lantz/drivers/cobolt/__init__.py
lantz/drivers/cobolt/cobolt0601.py
lantz/drivers/cobrite/cobritedx1.py
lantz/drivers/coherent/__init__.py
lantz/drivers/coherent/innova.py
lantz/drivers/dli/__init__.py
lantz/drivers/dli/webpowerswitch7.py
lantz/drivers/examples/__init__.py
lantz/drivers/examples/dummydrivers.py
lantz/drivers/examples/foreign_example.py
lantz/drivers/examples/fungen.py
lantz/drivers/examples/serial_example.py
lantz/drivers/examples/voltmeter.py
lantz/drivers/hinds/hindspem90.py
lantz_drivers.egg-info/PKG-INFO
lantz_drivers.egg-info/SOURCES.txt
lantz_drivers.egg-info/dependency_links.txt
lantz_drivers.egg-info/not-zip-safe
lantz_drivers.egg-info/requires.txt
lantz_drivers.egg-info/top_level.txt